[
  {
    "title": "[글로벌 포커스]돌아온 트럼프에 치열해진 美·中 패권 대결",
    "time": "8분 전",
    "link": "https://v.daum.net/v/20250401135817273",
    "category": "global"
  },
  {
    "title": "르펜 '출마금지 판결'에 佛 정국 안갯속…\"엄청난 정치적 분열\"",
    "time": "9분 전",
    "link": "https://v.daum.net/v/20250401135703217",
    "category": "global"
  },
  {
    "title": "\"韓 사회에 큰 충격\"...외신, 김수현 오열 기자회견 일제히 타진",
    "time": "29분 전",
    "link": "https://v.daum.net/v/20250401133711568",
    "category": "global"
  },
  {
    "title": "“이러다 ‘미국 내전’ 난다”…트럼프 ‘이 말’에 덜컥 겁먹은 네티즌",
    "time": "52분 전",
    "link": "https://v.daum.net/v/20250401131402895",
    "category": "global"
  },
  {
    "title": "의사도 내쫓는 미국…\"해외여행 다시 생각해\" 실리콘밸리 직원 단속",
    "time": "1시간 전",
    "link": "https://v.daum.net/v/20250401130147559",
    "category": "global"
  },
  {
    "title": "트럼프, 하버드 13조원 지원금 재검토…“반유대주의 방치해”",
    "time": "1시간 전",
    "link": "https://v.daum.net/v/20250401123634164",
    "category": "global"
  },
  {
    "title": "'액션영화 같은 점프!' 태국에서 '국민 남편' 된 한국인 남성 [World now]",
    "time": "2시간 전",
    "link": "https://v.daum.net/v/20250401122212848",
    "category": "global"
  },
  {
    "title": "말레이 쿠알라룸푸르 외곽서 가스관 폭발 대형 화재…33명 부상",
    "time": "5분 전",
    "link": "https://v.daum.net/v/20250401140115446",
    "category": "global"
  },
  {
    "title": "“한국 헌법재판소 탄핵선고일 지정” 외신 긴급 타전",
    "time": "9분 전",
    "link": "https://v.daum.net/v/20250401135720240",
    "category": "global"
  },
  {
    "title": "[글로벌D리포트] 도둑 들끓는 미국…보고도 신고 않는 시민들",
    "time": "12분 전",
    "link": "https://v.daum.net/v/20250401135414124",
    "category": "global"
  },
  {
    "title": "美, 日 車안전기준·IT기업 규제 등 지적…쌀 고관세도 비판",
    "time": "15분 전",
    "link": "https://v.daum.net/v/20250401135043996",
    "category": "global"
  },
  {
    "title": "“충돌 후 문 잠겼다”…中 전기차 폭발 후 전소, 3명 사망",
    "time": "15분 전",
    "link": "https://v.daum.net/v/20250401135042995",
    "category": "global"
  },
  {
    "title": "한국인도 많이 가는 日 유명 체인점서 '경악'...4일 긴급 휴점 [지금이뉴스]",
    "time": "20분 전",
    "link": "https://v.daum.net/v/20250401134621847",
    "category": "global"
  },
  {
    "title": "지진 붕괴 직전 52층 다리 뛰어넘은 한국인… “딸 구해야 한다는 생각만”",
    "time": "20분 전",
    "link": "https://v.daum.net/v/20250401134611842",
    "category": "global"
  },
  {
    "title": "韓대행, 4대그룹 총수와 TF회의…\"美상호관세에 긴급 지원조치\"(종합)",
    "time": "10분 전",
    "link": "https://v.daum.net/v/20250401135620186",
    "category": "global"
  },
  {
    "title": "윤 대통령 '운명' 손에 쥔 헌법재판관 8인의 면면",
    "time": "43분 전",
    "link": "https://v.daum.net/v/20250401132255148",
    "category": "global"
  },
  {
    "title": "중국군 ‘대만 포위’ 군사훈련 돌입…“독립 세력에 엄중한 경고”",
    "time": "1분 전",
    "link": "https://v.daum.net/v/20250401140508649",
    "category": "china"
  },
  {
    "title": "'3선' 열어놓는 트럼프…\"레임덕 피하고 대통령 권력 시험하기\"",
    "time": "2분 전",
    "link": "https://v.daum.net/v/20250401140400604",
    "category": "northamerica"
  },
  {
    "title": "미얀마 지진 속 일어난 기적…60시간 만에 구조된 여성 [숏폼]",
    "time": "1시간 전",
    "link": "https://v.daum.net/v/20250401130405597",
    "category": "asia"
  },
  {
    "title": "이스라엘, 가자 남부 라파흐에 대피 명령…“공격 재개 임박”",
    "time": "3시간 전",
    "link": "https://v.daum.net/v/20250401113009350",
    "category": "arab"
  },
  {
    "title": "유가 하락에 네옴시티 등 사우디 대형 프로젝트 ‘흔들’",
    "time": "3시간 전",
    "link": "https://v.daum.net/v/20250401111846670",
    "category": "arab"
  },
  {
    "title": "트럼프 \"핵포기 안하면 폭격·2차관세\" 위협에 이란 \"우릴 폭격하면 핵무장 불가피\"",
    "time": "3시간 전",
    "link": "https://v.daum.net/v/20250401110942190",
    "category": "arab"
  },
  {
    "title": "네타냐후 \"하마스 떠나면 가자서 '트럼프 계획' 실현\"",
    "time": "21시간 전",
    "link": "https://v.daum.net/v/20250331171625434",
    "category": "arab"
  },
  {
    "title": "인도주의단체 8명, 가자지구서 피살…이스라엘 \"하마스일 수도 있었다\"",
    "time": "23시간 전",
    "link": "https://v.daum.net/v/20250331144034899",
    "category": "arab"
  },
  {
    "title": "시리아 알샤라 대통령, 본격 과도내각 구성…'포용사회'",
    "time": "2일 전",
    "link": "https://v.daum.net/v/20250330222616000",
    "category": "arab"
  },
  {
    "title": "美국방부 새 전략…\"北 대응은 한국이 알아서\"",
    "time": "2일 전",
    "link": "https://v.daum.net/v/20250330174833267",
    "category": "arab"
  },
  {
    "title": "유엔 평화유지군에게도 기관총 쏜 이스라엘군",
    "time": "2일 전",
    "link": "https://v.daum.net/v/20250330162107770",
    "category": "arab"
  },
  {
    "title": "잠깐의 평화, 다시 울린 포성…이스라엘 ‘폭주’에 중동 다시 확전 [디브리핑]",
    "time": "2일 전",
    "link": "https://v.daum.net/v/20250330130017680",
    "category": "arab"
  },
  {
    "title": "NYT “이스라엘, 시리아·레바논 국경 너머에 감시초소 등 건설”",
    "time": "2시간 전",
    "link": "https://v.daum.net/v/20250401121842727",
    "category": "arab"
  },
  {
    "title": "가자 전쟁범죄 소굴됐나... \"이스라엘, 구호단체 민간인들 하나씩 살해\"",
    "time": "2시간 전",
    "link": "https://v.daum.net/v/20250401120014947",
    "category": "arab"
  },
  {
    "title": "‘카타르게이트’ 못 피하나… 네타냐후, 경찰조사 받아",
    "time": "2시간 전",
    "link": "https://v.daum.net/v/20250401115127564",
    "category": "arab"
  },
  {
    "title": "네타냐후 연정 극우 당수끼리 갈등…재무장관 사임",
    "time": "3시간 전",
    "link": "https://v.daum.net/v/20250401104421768",
    "category": "arab"
  },
  {
    "title": "이스라엘 가자지구 공격 재개로 사망자 늘어…이틀간 80명 사망",
    "time": "16시간 전",
    "link": "https://v.daum.net/v/20250331221500306",
    "category": "arab"
  },
  {
    "title": "\"트럼프 2기 첫 순방지도 사우디 … 5월중순 방문\"",
    "time": "20시간 전",
    "link": "https://v.daum.net/v/20250331180030424",
    "category": "arab"
  },
  {
    "title": "[맵 브리핑] 시리아, 과도정부 개각…여성 장관 깜짝 포함",
    "time": "22시간 전",
    "link": "https://v.daum.net/v/20250331155018384",
    "category": "arab"
  },
  {
    "title": "\"우크라 전쟁과 무관하다\"지만… 푸틴, '14년 만에 최대 춘계 징병'",
    "time": "2시간 전",
    "link": "https://v.daum.net/v/20250401123002008",
    "category": "europe"
  },
  {
    "title": "커지는 '우크라 휴전 데드라인 설정' 목소리… 유럽 주요국도 합류",
    "time": "2시간 전",
    "link": "https://v.daum.net/v/20250401121013472",
    "category": "europe"
  },
  {
    "title": "거세지는 빅테크 역할론… EU ‘DNA법’으로 분쟁 대비 [심층기획-다시 불붙은 '망 사용료' 논쟁]",
    "time": "8시간 전",
    "link": "https://v.daum.net/v/20250401060218274",
    "category": "europe"
  },
  {
    "title": "'대서양 가교' 자임 멜로니 伊총리, 트럼프 기댔다가 진퇴양난",
    "time": "11시간 전",
    "link": "https://v.daum.net/v/20250401032535117",
    "category": "europe"
  },
  {
    "title": "핀란드 대통령 \"트럼프, 푸틴 휴전 불응에 짜증 · 불만\"",
    "time": "11시간 전",
    "link": "https://v.daum.net/v/20250401025700971",
    "category": "europe"
  },
  {
    "title": "우크라, '광물협정' 변경 추진…\"미국 우선접근권 수정\"",
    "time": "13시간 전",
    "link": "https://v.daum.net/v/20250401005423631",
    "category": "europe"
  },
  {
    "title": "英·EU 관계 재설정 위한 방위협정 5월 돌파구 기대",
    "time": "18시간 전",
    "link": "https://v.daum.net/v/20250331195531012",
    "category": "europe"
  },
  {
    "title": "獨 메르츠, EU서 '러 규탄 독자반대' 헝가리 압박 강화 구상",
    "time": "20시간 전",
    "link": "https://v.daum.net/v/20250331175405141",
    "category": "europe"
  },
  {
    "title": "리투아니아서 임무중 실종된 미군 3명 숨진채 발견",
    "time": "2시간 전",
    "link": "https://v.daum.net/v/20250401115117553",
    "category": "europe"
  },
  {
    "title": "폴란드 총리, 트럼프 상호관세 임박에 \"대립보다 협력\"…막판 호소",
    "time": "3시간 전",
    "link": "https://v.daum.net/v/20250401105143186",
    "category": "europe"
  },
  {
    "title": "\"불법 이민에 분노한다\" 영국서 40개국·기술기업 회의",
    "time": "18시간 전",
    "link": "https://v.daum.net/v/20250331194521803",
    "category": "europe"
  },
  {
    "title": "ECB 총재 \"트럼프 '해방의 날' 4월2일…유럽의 경제독립 첫날\"",
    "time": "21시간 전",
    "link": "https://v.daum.net/v/20250331173111200",
    "category": "europe"
  },
  {
    "title": "\"젤렌스키, 휴전 뒤 대선 준비 지시\"… 7월 초 선거 가능성",
    "time": "21시간 전",
    "link": "https://v.daum.net/v/20250331171039171",
    "category": "europe"
  },
  {
    "title": "EU는 꺼리는 美 F-35 전투기…\"英, 수십억불 규모 구매 예정\"",
    "time": "23시간 전",
    "link": "https://v.daum.net/v/20250331152437072",
    "category": "europe"
  },
  {
    "title": "네타냐후, ICC 체포영장 아랑곳않고 해외방문…헝가리 \"환영\"",
    "time": "23시간 전",
    "link": "https://v.daum.net/v/20250331143926846",
    "category": "europe"
  }
]